{
  "packages": {
    "backend": {
      "release-type": "go",
      "package-name": "chartimpact-backend",
      "changelog-path": "CHANGELOG.md",
      "bump-minor-pre-major": true,
      "bump-patch-for-minor-pre-major": true
    },
    "frontend": {
      "release-type": "node",
      "package-name": "chartimpact-frontend",
      "changelog-path": "CHANGELOG.md",
      "bump-minor-pre-major": true,
      "bump-patch-for-minor-pre-major": true
    }
  },
  "separate-pull-requests": true,
  "group-pull-request-title-pattern": "chore: release ${version}",
  "changelog-sections": [
    { "type": "feat", "section": "Features" },
    { "type": "fix", "section": "Bug Fixes" },
    { "type": "perf", "section": "Performance Improvements" },
    { "type": "revert", "section": "Reverts" },
    { "type": "docs", "section": "Documentation" },
    { "type": "style", "section": "Styles", "hidden": true },
    { "type": "chore", "section": "Miscellaneous Chores", "hidden": true },
    { "type": "refactor", "section": "Code Refactoring", "hidden": true },
    { "type": "test", "section": "Tests", "hidden": true },
    { "type": "build", "section": "Build System", "hidden": true },
    { "type": "ci", "section": "Continuous Integration", "hidden": true }
  ]
}
